g2pkk/__init__.py
g2pkk/english.py
g2pkk/g2pkk.py
g2pkk/idioms.txt
g2pkk/numerals.py
g2pkk/regular.py
g2pkk/rules.txt
g2pkk/special.py
g2pkk/table.csv
g2pkk/utils.py
g2pkk-0.1.2.dist-info/LICENSE
g2pkk-0.1.2.dist-info/METADATA
g2pkk-0.1.2.dist-info/WHEEL
g2pkk-0.1.2.dist-info/top_level.txt
g2pkk-0.1.2.dist-info/RECORD
