Metadata-Version: 2.1
Name: g2pkk
Version: 0.1.2
Summary: g2pkk: g2p module for Korean(cross platform)
Home-page: https://github.com/harmlessman/g2pkk
Author: harmlessman
Author-email: harmlessman17@gmail.com
License: Apache License 2.0
Classifier: Development Status :: 5 - Production/Stable
Classifier: Intended Audience :: Developers
Classifier: Intended Audience :: Science/Research
Classifier: License :: OSI Approved :: Apache Software License
Classifier: Operating System :: OS Independent
Classifier: Programming Language :: Python :: 3
Classifier: Programming Language :: Python :: 3.6
Classifier: Programming Language :: Python :: 3.7
Requires-Python: >=3.6
License-File: LICENSE
